ditto_client/__about__.py
ditto_client/__init__.py
ditto_client/__main__.py
ditto_client/_basic_auth.py
ditto_client/cli/__init__.py
ditto_client/cli/_devops.py
ditto_client/cli/_permission.py
ditto_client/cli/_policy.py
ditto_client/cli/_search.py
ditto_client/cli/_thing.py
ditto_client/cli/devops/__init__.py
ditto_client/cli/devops/_config.py
ditto_client/cli/devops/_connection.py
ditto_client/cli/devops/_logging.py
ditto_client/generated/ditto_client.py
ditto_client/generated/kiota-lock.json
ditto_client/generated/api/api_request_builder.py
ditto_client/generated/api/two/two_request_builder.py
ditto_client/generated/api/two/check_permissions/check_permissions_request_builder.py
ditto_client/generated/api/two/cloudevents/cloudevents_post_request_body.py
ditto_client/generated/api/two/cloudevents/cloudevents_post_request_body_headers.py
ditto_client/generated/api/two/cloudevents/cloudevents_post_request_body_value.py
ditto_client/generated/api/two/cloudevents/cloudevents_post_request_body_value_member1.py
ditto_client/generated/api/two/cloudevents/cloudevents_post_request_body_value_member2.py
ditto_client/generated/api/two/cloudevents/cloudevents_request_builder.py
ditto_client/generated/api/two/connections/connections_request_builder.py
ditto_client/generated/api/two/connections/item/with_connection_item_request_builder.py
ditto_client/generated/api/two/connections/item/command/command_request_builder.py
ditto_client/generated/api/two/connections/item/logs/logs_request_builder.py
ditto_client/generated/api/two/connections/item/metrics/metrics_request_builder.py
ditto_client/generated/api/two/connections/item/status/status_request_builder.py
ditto_client/generated/api/two/policies/policies_request_builder.py
ditto_client/generated/api/two/policies/item/with_policy_item_request_builder.py
ditto_client/generated/api/two/policies/item/actions/actions_request_builder.py
ditto_client-0.3.0.dist-info/METADATA
ditto_client-0.3.0.dist-info/WHEEL
ditto_client-0.3.0.dist-info/entry_points.txt
ditto_client-0.3.0.dist-info/licenses/LICENSE
ditto_client-0.3.0.dist-info/RECORD
